mypythonpackageblablabla/__init__.py
mypythonpackageblablabla/greet.py
mypythonpackageblablabla/mymath.py
mypythonpackageblablabla-0.1.dist-info/METADATA
mypythonpackageblablabla-0.1.dist-info/WHEEL
mypythonpackageblablabla-0.1.dist-info/top_level.txt
mypythonpackageblablabla-0.1.dist-info/RECORD
