Metadata-Version: 2.1
Name: mypythonpackageblablabla
Version: 0.1
Summary: my first Python package
Home-page: https://github.com/daimessdn
Author: dimaswehhh
Author-email: daimessdn@gmail.com
License: UNKNOWN
Platform: UNKNOWN
